LICENSE
MANIFEST.in
README.md
pyproject.toml
setup.py
deriv/__init__.py
deriv/engine.py
deriv.egg-info/PKG-INFO
deriv.egg-info/SOURCES.txt
deriv.egg-info/dependency_links.txt
deriv.egg-info/not-zip-safe
deriv.egg-info/top_level.txt
deriv/math/__init__.py
deriv/math/math_cpu.cpp
deriv/math/math_cpu.pxd
deriv/math/math_cpu.pyx
deriv/math/matrix_cpu.cpp
deriv/math/matrix_cpu.pxd
deriv/math/matrix_cpu.pyx
deriv/nn/__init__.py
deriv/nn/non_linear.cpp
deriv/nn/non_linear.pyx
deriv/utils/__init__.py
deriv/utils/helpers.cpp
deriv/utils/helpers.pxd
deriv/utils/helpers.pyx
deriv/utils/util_excp.py